[
    {
        "Banks": "UBS ex Overlay",
        "YTD": "0.23850070952502733",
        "3 Mos": "0.06091118109458504",
        "1Yr": "0.2365662480603754",
        "AVOS": ""
    },
    {
        "Banks": "MS ex Overlay",
        "YTD": "0.25451353272308364",
        "3 Mos": "0.061103758251968676",
        "1Yr": "0.21570787649242718",
        "AVOS": ""
    },
    {
        "Banks": "Current Portfolio",
        "YTD": "0.21333140472773682",
        "3 Mos": "",
        "1Yr": "",
        "AVOS": "0.20449776683021903"
    },
    {
        "Banks": "Beta Alone Portfolio",
        "YTD": "0.24408377980937468",
        "3 Mos": "",
        "1Yr": "",
        "AVOS": "0.26620951665400305"
    },
    {
        "Banks": "AVOS",
        "YTD": "0.18972122713631134",
        "3 Mos": "",
        "1Yr": "",
        "AVOS": "0.21245865425251864"
    }
]